{"cameraMode":{"drawMode":0,"name":"Shaded","section":"Shading Mode"},"sceneLighting":false,"audioPlay":false,"sceneViewState":{"m_AlwaysRefresh":false,"showFog":true,"showSkybox":false,"showFlares":true,"showImageEffects":true,"showParticleSystems":true,"showVisualEffectGraphs":true,"m_FxEnabled":true},"in2DMode":false,"pivot":{"x":724.0,"y":1280.0,"z":0.0},"rotation":{"x":0.055356141179800037,"y":-0.9429135322570801,"z":0.20097605884075166,"w":0.2597362995147705},"size":258.8744812011719,"orthographic":false}